setup.py
trouble/__init__.py
trouble.egg-info/PKG-INFO
trouble.egg-info/SOURCES.txt
trouble.egg-info/dependency_links.txt
trouble.egg-info/top_level.txt