Metadata-Version: 1.0
Name: trouble
Version: 0.8
Summary: The model and corpus files for trouble.whoahbot.com
Home-page: http://github.com/whoahbot/trouble/
Author: Dan Herrera
Author-email: whoahbot@gmail.com
License: UNKNOWN
Platform: UNKNOWN
